PyMailService/__init__.py
PyMailService/email_reader.py
PyMailService/main.py
PyMailService/standart_setting.py
PyMailService-0.0.2.dist-info/LICENSE
PyMailService-0.0.2.dist-info/METADATA
PyMailService-0.0.2.dist-info/WHEEL
PyMailService-0.0.2.dist-info/top_level.txt
PyMailService-0.0.2.dist-info/RECORD
