Metadata-Version: 2.1
Name: PyMailService
Version: 0.0.2
Summary: The library allows you to view, receive, and send emails.
Author-email: Dan2_il <daniilgr97@yandex.ru>
Project-URL: Homepage, https://github.com/Dan2il/PyMailService
Classifier: Programming Language :: Python :: 3
Classifier: License :: OSI Approved :: MIT License
Classifier: Operating System :: OS Independent
Requires-Python: >=3.10
License-File: LICENSE
